MANIFEST.in
setup.cfg
setup.py
secret/__init__.py
secret/algo.py
secret/cli.py
secret/middleware.py
secret/output.py
secret/project.py
secret/secret.py
secret/storage.py
secret/templates.py
secret/vault.py
secret_python3.egg-info/PKG-INFO
secret_python3.egg-info/SOURCES.txt
secret_python3.egg-info/dependency_links.txt
secret_python3.egg-info/entry_points.txt
secret_python3.egg-info/requires.txt
secret_python3.egg-info/top_level.txt