Metadata-Version: 1.1
Name: secret-python3
Version: 0.7
Summary: Secret is for storing secrets. Backed by Amazon Web Services: IAM for access policies, KMS for encryption keys and S3 for storage
Home-page: https://github.com/futurice/secret
Author: Jussi Vaihia
Author-email: jussi.vaihia@futurice.com
License: Apache2
Keywords: secret secrets project vault aws amazon cloud
Platform: UNKNOWN
Classifier: Intended Audience :: Developers
Classifier: License :: OSI Approved :: Apache Software License
